coasti/__init__.py
coasti/coasti.py
coasti-0.1.1.dist-info/METADATA
coasti-0.1.1.dist-info/WHEEL
coasti-0.1.1.dist-info/entry_points.txt
coasti-0.1.1.dist-info/top_level.txt
coasti-0.1.1.dist-info/RECORD
