Metadata-Version: 2.4
Name: coasti
Version: 0.1.1
Summary: Installer for Coasti, the Open-Source Business Intelligence Framework
Requires-Python: <3.13,>=3.9
Requires-Dist: python-dotenv==1.0.1
Requires-Dist: typer==0.15.2
Requires-Dist: PyYAML==6.0.2
Requires-Dist: ruamel.yaml==0.18.10
Requires-Dist: xkcdpass>=1.20
